aceternity/__init__.py
aceternity/main.py
aceternity/mcp.json
aceternity-0.1.0.dist-info/METADATA
aceternity-0.1.0.dist-info/WHEEL
aceternity-0.1.0.dist-info/entry_points.txt
aceternity-0.1.0.dist-info/top_level.txt
aceternity-0.1.0.dist-info/RECORD
